elkAnalyzer/DOS.py
elkAnalyzer/__init__.py
elkAnalyzer/bands.py
elkAnalyzer/specialPoints.py
elkAnalyzer-0.0.2.dist-info/LICENSE
elkAnalyzer-0.0.2.dist-info/METADATA
elkAnalyzer-0.0.2.dist-info/WHEEL
elkAnalyzer-0.0.2.dist-info/top_level.txt
elkAnalyzer-0.0.2.dist-info/RECORD
