Metadata-Version: 2.1
Name: elkAnalyzer
Version: 0.0.2
Summary: A small package for analyzing Elk outputs
Home-page: https://github.com/euclidmenot2/elkAnalyzer
Author: Elizabeth Pogue
Author-email: epogue1@jhu.edu
License: UNKNOWN
Keywords: elk,dft
Platform: UNKNOWN
Classifier: Programming Language :: Python :: 3
Classifier: License :: OSI Approved :: MIT License
Classifier: Operating System :: OS Independent
Requires-Python: >=3.6
